sphinx_tfdoc/__init__.py
sphinx_tfdoc/extension.py
sphinx_tfdoc/store.py
sphinx_tfdoc/templates/base.rst
sphinx_tfdoc/templates/data_resource.rst
sphinx_tfdoc/templates/index.rst
sphinx_tfdoc/templates/managed_resource.rst
sphinx_tfdoc/templates/module.rst
sphinx_tfdoc/templates/module_call.rst
sphinx_tfdoc/templates/output.rst
sphinx_tfdoc/templates/required_provider.rst
sphinx_tfdoc/templates/variable.rst
sphinx_tfdoc/terraform.py
sphinx_tfdoc-0.1.0.dist-info/WHEEL
sphinx_tfdoc-0.1.0.dist-info/METADATA
sphinx_tfdoc-0.1.0.dist-info/RECORD
